oc_art_to_ftp/__init__.py
oc_art_to_ftp/config.py
oc_art_to_ftp/sync.py
oc_art_to_ftp/wsgi.py
oc_art_to_ftp-1.1.4.data/scripts/sync.py
oc_art_to_ftp-1.1.4.dist-info/licenses/LICENSE
oc_art_to_ftp-1.1.4.dist-info/METADATA
oc_art_to_ftp-1.1.4.dist-info/WHEEL
oc_art_to_ftp-1.1.4.dist-info/top_level.txt
oc_art_to_ftp-1.1.4.dist-info/RECORD
